src/__init__.py
src/mapply.py
mpandas-0.0.2.1.dist-info/LICENSE
mpandas-0.0.2.1.dist-info/METADATA
mpandas-0.0.2.1.dist-info/WHEEL
mpandas-0.0.2.1.dist-info/top_level.txt
mpandas-0.0.2.1.dist-info/RECORD
