Metadata-Version: 2.1
Name: mpandas
Version: 0.0.2.1
Summary: Use pandas with multiprocessing
Author: Shin Chen
Author-email: <jiayuanchen@outlook.com>
Keywords: python,pandas,multiprocessing
License-File: LICENSE
Requires-Dist: pandas
